Lab0/half_adder.v
`timescale 1ns / 1ps

module Half_Adder(
    In_A, In_B, Sum, Carry_out
    );
    input In_A, In_B;
    output Sum, Carry_out;
    
    // implement half adder circuit, your code starts from here.
	// gate(output, input1, input2)
    xor(, , );
	and(, , );
	
endmodule

Lab0/full_adder.v
`timescale 1ns / 1ps

module Full_Adder(
    In_A, In_B, Carry_in, Sum, Carry_out
    );
    input In_A, In_B, Carry_in;
    output Sum, Carry_out;
    
	// implement full adder circuit, your code starts from here.
	// use half adder in this module, fulfill I/O ports connection.
    wire W1, W2, W3;

    Half_Adder HAD1 (
        .In_A(In_A),
        .In_B(In_B),
        .Sum(W1),
        .Carry_out(W2)
    );


    Half_Adder HAD2 (
        .In_A(W1),
        .In_B(Carry_in),
        .Sum(Sum),
        .Carry_out(W3)
    );

    or or1(Carry_out, W2, W3);
    
    
endmodule

Lab0/testbench.v
module testbench;

reg a, b, cin; // for stimulus waveforms
wire sum, c_out;

// correct answer
reg [7:0]ans_sum;
reg [7:0]ans_carry;
reg correct, clk;
reg [7:0]counter;
// for testing half adder
//Half_Adder HAD (a, b, sum, c_out);

// for testing full adder
Full_Adder FAD (a, b, cin, sum, c_out);

initial #100 $finish; // Stopwatch
initial begin // Stimulus patterns
    clk = 1'b0;
    counter =  8'd8;
    correct = 1;
    ans_sum     = 8'b01101001;
    ans_carry   = 8'b00010111;
    
    #10 a = 0; b = 0; cin = 0; // Statements execute in sequence
    #10 a = 0; b = 1; cin = 0;
    #10 a = 1; b = 0; cin = 0;
    #10 a = 1; b = 1; cin = 0;
    #10 a = 0; b = 0; cin = 1;
    #10 a = 0; b = 1; cin = 1; 
    #10 a = 1; b = 0; cin = 1; 
    #10 a = 1; b = 1; cin = 1; 
end

always #5 clk = ~clk;

always@(posedge clk) begin
    if($signed(counter) <= 7 && !(ans_sum[counter] === sum) || !(ans_carry[counter] === c_out)) begin
        $display(" Pattern %d is wrong! ", counter);
        $display(" sum %d ans %d ", sum, ans_sum[counter]);
        $display(" car %d ans %d ", c_out, ans_carry[counter]);
        correct = 0;
    end
    if (counter == 0 && correct) begin
        $display("***************************************************");
        $display(" Congratulation! All data are correct! ");
        $display("***************************************************");
        correct = 0;
    end
    if(counter != 0)
        counter <= counter - 8'd1;
    else
        counter <= counter;
end

initial begin
    $dumpfile("gtkWave.vcd");
    $dumpvars;
end


endmodule

Lab0/gtkWave.vcd
$date
	Fri Mar 12 10:19:21 2021
$end
$version
	Icarus Verilog
$end
$timescale
	1ps
$end
$scope module testbench $end
$var wire 1 ! sum $end
$var wire 1 " c_out $end
$var reg 1 # a $end
$var reg 8 $ ans_carry [7:0] $end
$var reg 8 % ans_sum [7:0] $end
$var reg 1 & b $end
$var reg 1 ' cin $end
$var reg 1 ( clk $end
$var reg 1 ) correct $end
$var reg 8 * counter [7:0] $end
$scope module FAD $end
$var wire 1 ' Carry_in $end
$var wire 1 " Carry_out $end
$var wire 1 # In_A $end
$var wire 1 & In_B $end
$var wire 1 + W3 $end
$var wire 1 , W2 $end
$var wire 1 - W1 $end
$var wire 1 ! Sum $end
$scope module HAD1 $end
$var wire 1 , Carry_out $end
$var wire 1 # In_A $end
$var wire 1 & In_B $end
$var wire 1 - Sum $end
$upscope $end
$scope module HAD2 $end
$var wire 1 + Carry_out $end
$var wire 1 - In_A $end
$var wire 1 ' In_B $end
$var wire 1 ! Sum $end
$upscope $end
$upscope $end
$upscope $end
$enddefinitions $end
#0
$dumpvars
x-
x,
x+
b1000 *
1)
0(
x'
x&
b1101001 %
b10111 $
x#
x"
x!
$end
#5000
b111 *
1(
#10000
0"
0!
0+
0-
0,
0(
0'
0&
0#
#15000
b110 *
1(
#20000
1!
1-
0(
1&
#25000
b101 *
1(
#30000
0(
0&
1#
#35000
b100 *
1(
#40000
0!
1"
0-
1,
0(
1&
#45000
b11 *
1(
#50000
0"
1!
0,
0(
1'
0&
0#
#55000
b10 *
1(
#60000
1"
0!
1+
1-
0(
1&
#65000
b1 *
1(
#70000
0(
0&
1#
#75000
b0 *
1(
#80000
1!
0+
0-
1,
0(
1&
#85000
0)
1(
