Lab4-Pipelined CPU/MUX_2to1.v
`timescale 1ns/1ps
module MUX_2to1(
   data0_i,
   data1_i,
   select_i,
   data_o
);

parameter size = 0;			   
			
// I/O ports               
input   [size-1:0] data0_i;          
input   [size-1:0] data1_i;
input              select_i;
output  [size-1:0] data_o; 

// Internal Signals
reg     [size-1:0] data_o;

// Main function

always @(*) begin
	data_o <= select_i ? data1_i : data0_i;
end

endmodule

Lab4-Pipelined CPU/Shift_Left_Two_32.v
// 0816153

`timescale 1ns/1ps
module Shift_Left_Two_32(
    data_i,
    data_o
);

//I/O ports                    
input [32-1:0] data_i;
output [32-1:0] data_o;

//shift left 2

assign data_o[31:2] = data_i[29:0];
assign data_o[ 1:0] = 2'b00;

endmodule

Lab2-Singel Cycle CPU/Adder.v
`timescale 1ns/1ps
module Adder(
    src1_i,
	src2_i,
	sum_o
);
     
//I/O ports
input  [32-1:0]  src1_i;
input  [32-1:0]	 src2_i;
output [32-1:0]	 sum_o;

//Internal Signals
reg    [32-1:0]	 sum_o;

    
//Main function
always @(*) begin 
	sum_o = src1_i + src2_i;
end

endmodule

Lab2-Singel Cycle CPU/ALU.v
`timescale 1ns/1ps
module ALU(
    src1_i,
	src2_i,
	ctrl_i,
	result_o,
	zero_o
);
     
//IO ports
input signed [32-1:0]  src1_i;
input signed [32-1:0]  src2_i;
input  [4-1:0]   ctrl_i;

output [32-1:0]	 result_o;
output           zero_o;

//Internal signals
reg    [32-1:0]  result_o;
wire             zero_o;

assign zero_o = (result_o == 0);

always @(ctrl_i, src1_i, src2_i) begin
	case (ctrl_i)
		0 : result_o <= src1_i & src2_i;
		1 : result_o <= src1_i | src2_i;
		2 : result_o <= src1_i + src2_i;
		6 : result_o <= src1_i - src2_i;
		7 : result_o <= (src1_i < src2_i ? 1 : 0);
		12: result_o <= ~(src1_i | src2_i);
		default: result_o <= 0;
	endcase
end

endmodule

Lab3-Single Cycle CPU (Complete Ed.)/Sign_Extend.v
//Subject:     CO project 2 - Sign extend
//--------------------------------------------------------------------------------
//Version:     1
//--------------------------------------------------------------------------------
//Writer:      
//----------------------------------------------
//Date:        
//----------------------------------------------
//Description: 
//--------------------------------------------------------------------------------
`timescale 1ns/1ps
module Sign_Extend(
    data_i,
    data_o
    );
               
// I/O ports
input   [16-1:0] data_i;
output  [32-1:0] data_o;

// Internal Signals
reg     [32-1:0] data_o;

// Sign extended

always @(*) begin 
	data_o[15: 0] = data_i[15:0];
	if (data_i[15] == 1'b0) begin
		data_o[31:16] = 16'd0;		
	end
	else begin
		data_o[31:16] = 16'b1111111111111111;
	end
end

endmodule

Lab2-Singel Cycle CPU/ALU_Ctrl.v
//Subject:     CO project 2 - ALU Controller
//--------------------------------------------------------------------------------
//Version:     1
//--------------------------------------------------------------------------------
//Writer:      
//----------------------------------------------
//Date:        
//----------------------------------------------
//Description: 
//--------------------------------------------------------------------------------
`timescale 1ns/1ps
module ALU_Ctrl(
    funct_i,
    ALUOp_i,
    ALUCtrl_o
);
          
//I/O ports 
input      [6-1:0] funct_i;
input      [3-1:0] ALUOp_i;

output     [4-1:0] ALUCtrl_o;    
     
//Internal Signals
reg        [4-1:0] ALUCtrl_o;

//Parameter
wire op0 = (funct_i[0] | funct_i[3]) & ALUOp_i[1];
wire op1 = (~funct_i[2]) | (~ALUOp_i[1]);
wire op2 = (funct_i[1] & ALUOp_i[1])  | ALUOp_i[0];
wire op3 = 1'b0;

//Select exact operation
always @(*) begin
	// Not addi or slti, -> R-format & Beq
	if (ALUOp_i[2] == 1'b0) begin
		ALUCtrl_o[3] <= op3;
		ALUCtrl_o[2] <= op2;
		ALUCtrl_o[1] <= op1;
		ALUCtrl_o[0] <= op0;
	end
	else begin
		case(ALUOp_i)
			3'b110: ALUCtrl_o <= 4'b0010;
			3'b101: ALUCtrl_o <= 4'b0111;
			default:
				ALUCtrl_o = 4'b0000;
		endcase
	end
end

endmodule

Lab3-SC CPU (Complete Ed.)/Decoder.v
`timescale 1ns/1ps
module Decoder(
    instr_op_i,
	RegWrite_o,
	ALU_op_o,
	ALUSrc_o,
	RegDst_o,
	Branch_o
);
     
// I/O ports
input  [6-1:0] instr_op_i;

output         RegWrite_o;
output [3-1:0] ALU_op_o;
output         ALUSrc_o;
output         RegDst_o;
output         Branch_o;
 
// Internal Signals
reg    [3-1:0] ALU_op_o;
reg            ALUSrc_o;
reg            RegWrite_o;
reg            RegDst_o;
reg            Branch_o;

// Parameter

// R-format 000,000
wire rfmt = (~instr_op_i[5]) & (~instr_op_i[4]) & (~instr_op_i[3]) &
			(~instr_op_i[2]) & (~instr_op_i[1]) & (~instr_op_i[0]);

// Addi 001,000
wire addi = (~instr_op_i[5]) & (~instr_op_i[4]) & ( instr_op_i[3]) &
			(~instr_op_i[2]) & (~instr_op_i[1]) & (~instr_op_i[0]);

// slti 001,010
wire slti = (~instr_op_i[5]) & (~instr_op_i[4]) & ( instr_op_i[3]) &
			(~instr_op_i[2]) & ( instr_op_i[1]) & (~instr_op_i[0]);

// beq 000,100
wire bieq = (~instr_op_i[5]) & (~instr_op_i[4]) & (~instr_op_i[3]) &
			( instr_op_i[2]) & (~instr_op_i[1]) & (~instr_op_i[0]);

always @(*) begin 
	RegDst_o <= rfmt;
	RegWrite_o <= rfmt | addi | slti;
	Branch_o <= bieq;
	ALUSrc_o <= addi | slti;
end

// ALU_OP
always @(*) begin
	case(instr_op_i)
		6'b001000: ALU_op_o <= 3'b110;
		6'b001010: ALU_op_o <= 3'b101;
		6'b000000: ALU_op_o <= 3'b010;
		6'b000100: ALU_op_o <= 3'b001;
		default:
			ALU_op_o <= 3'b000;
	endcase
end

endmodule

Lab5-Advanced Pipe CPU/Reg_File.v
`timescale 1ns / 1ps

module Reg_File(
    clk_i,
    rst_i,
    RSaddr_i,
    RTaddr_i,
    RDaddr_i,
    RDdata_i,
    RegWrite_i,
    RSdata_o,
    RTdata_o
);
          
//I/O ports
input               clk_i;
input               rst_i;
input               RegWrite_i;
input   [5-1:0]     RSaddr_i;
input   [5-1:0]     RTaddr_i;
input   [5-1:0]     RDaddr_i;
input   [32-1:0]    RDdata_i;

output  [32-1:0]    RSdata_o;
output  [32-1:0]    RTdata_o;   

//Internal signals/registers           
reg signed  [32-1:0] Reg_File [0:32-1]; //32 word registers
wire        [32-1:0] RSdata_o;
wire        [32-1:0] RTdata_o;

//Read the data
assign  RSdata_o = Reg_File[RSaddr_i];
assign  RTdata_o = Reg_File[RTaddr_i];   

//Writing data when negedge clk_i and RegWrite_i was set.
always@( negedge clk_i or posedge rst_i)
begin
    if(rst_i == 0)
    begin
        Reg_File[0]  <= 0; Reg_File[1]  <= 0; Reg_File[2]  <= 0; Reg_File[3]  <= 0;
        Reg_File[4]  <= 0; Reg_File[5]  <= 0; Reg_File[6]  <= 0; Reg_File[7]  <= 0;
        Reg_File[8]  <= 0; Reg_File[9]  <= 0; Reg_File[10] <= 0; Reg_File[11] <= 0;
        Reg_File[12] <= 0; Reg_File[13] <= 0; Reg_File[14] <= 0; Reg_File[15] <= 0;
        Reg_File[16] <= 0; Reg_File[17] <= 0; Reg_File[18] <= 0; Reg_File[19] <= 0;      
        Reg_File[20] <= 0; Reg_File[21] <= 0; Reg_File[22] <= 0; Reg_File[23] <= 0;
        Reg_File[24] <= 0; Reg_File[25] <= 0; Reg_File[26] <= 0; Reg_File[27] <= 0;
        Reg_File[28] <= 0; Reg_File[29] <= 0; Reg_File[30] <= 0; Reg_File[31] <= 0;
    end
    else
    begin
        if(RegWrite_i) 
            Reg_File[RDaddr_i] <= RDdata_i;	
        else 
            Reg_File[RDaddr_i] <= Reg_File[RDaddr_i];
    end
end

endmodule

Lab2-Singel Cycle CPU/Instr_Memory.v
`timescale 1ns/1ps
module Instr_Memory(
    pc_addr_i,
	instr_o
);
 
//I/O ports
input  [32-1:0]  pc_addr_i;
output [32-1:0]	 instr_o;

//Internal Signals
reg    [32-1:0]	 instr_o;
integer          i;

//32 words Memory
reg    [32-1:0]  Instr_Mem [0:32-1];

//Parameter
    
//Main function
always @(pc_addr_i) begin
	instr_o = Instr_Mem[pc_addr_i/4];
end
    
//Initial Memory Contents
initial begin
    for ( i=0; i<32; i=i+1 )
		Instr_Mem[i] = 32'b0;

	// Read instruction from "CO_P2_test_data1.txt"
    $readmemb("./testcase/CO_P2_test_data2.txt", Instr_Mem);
end
endmodule

Lab2-Singel Cycle CPU/ProgramCounter.v
`timescale 1ns/1ps
module ProgramCounter(
    clk_i,
	rst_i,
	pc_in_i,
	pc_out_o
	);
     
//I/O ports
input           clk_i;
input	        rst_i;
input  [32-1:0] pc_in_i;
output [32-1:0] pc_out_o;
 
//Internal Signals
reg    [32-1:0] pc_out_o;
 
//Main function
always @(posedge clk_i) begin
    if(~rst_i)
	    pc_out_o <= 0;
	else
	    pc_out_o <= pc_in_i;
end

endmodule

Lab3-SC CPU (Complete Ed.)/Simple_Single_CPU.v
`timescale 1ns/1ps

module Simple_Single_CPU(
    clk_i,
	rst_i
);
		
// I/O port
input   clk_i;
input   rst_i;

// Internal Signles

wire [32-1:0] pc;
wire [32-1:0] nxt_pc0, nxt_pc1, fin_pc;

// Greate componentes
ProgramCounter PC(
    .clk_i(clk_i),      
    .rst_i (rst_i),     
    .pc_in_i(fin_pc) ,   
	.pc_out_o(pc) 
);

Adder Adder1(
    .src1_i(32'd4),     
    .src2_i(pc),     
    .sum_o(nxt_pc0)    
);

wire [32-1:0] instr;

Instr_Memory IM(
    .pc_addr_i(pc),  
    .instr_o(instr)
);

wire [5-1:0] wrt_reg;

wire RegDst, RegWrite, Branch;
wire [3-1:0] aluOp;
wire aluSrc;

MUX_2to1 #(.size(5)) Mux_Write_Reg(
    .data0_i(instr[20:16]),
    .data1_i(instr[15:11]),
    .select_i(RegDst),
    .data_o(wrt_reg)
);	

wire [32-1:0] rd1, rd2;
wire [32-1:0] wrt_dat;

Reg_File RF(
    .clk_i(clk_i),      
    .rst_i(rst_i) ,     
    .RSaddr_i(instr[25:21]) ,  
    .RTaddr_i(instr[20:16]) ,  
    .RDaddr_i(wrt_reg),  
    .RDdata_i(wrt_dat)  , 
    .RegWrite_i (RegWrite),
    .RSdata_o(rd1) ,  
    .RTdata_o(rd2)   
);

Decoder Decoder(
    .instr_op_i(instr[31:26]), 
    .RegWrite_o(RegWrite), 
    .ALU_op_o(aluOp),   
    .ALUSrc_o(aluSrc),   
    .RegDst_o(RegDst),   
	.Branch_o(Branch)
);

wire [4-1:0] aluCTtoalu;

ALU_Ctrl AC(
    .funct_i(instr[5:0]),   
    .ALUOp_i(aluOp),   
    .ALUCtrl_o(aluCTtoalu) 
);

wire [32-1:0] aft_sgn;

Sign_Extend SE(
    .data_i(instr[15:0]),
    .data_o(aft_sgn)
);

wire [32-1:0] alu_src;

MUX_2to1 #(.size(32)) Mux_ALUSrc(
    .data0_i(rd2),
    .data1_i(aft_sgn),
    .select_i(aluSrc),
    .data_o(alu_src)
);
		
wire zeo;

ALU ALU(
    .src1_i(rd1),
    .src2_i(alu_src),
    .ctrl_i(aluCTtoalu),
    .result_o(wrt_dat),
	.zero_o(zeo)
);

wire [32-1:0] aft_sft;

Adder Adder2(
    .src1_i(nxt_pc0),     
    .src2_i(aft_sft),     
    .sum_o(nxt_pc1)      
);
		
Shift_Left_Two_32 Shifter(
    .data_i(aft_sgn),
    .data_o(aft_sft)
); 		

wire nxt_slc;

and pcSLC(nxt_slc, Branch, zeo);
	
MUX_2to1 #(.size(32)) Mux_PC_Source(
    .data0_i(nxt_pc0),
    .data1_i(nxt_pc1),
    .select_i(nxt_slc),
    .data_o(fin_pc)
);	

endmodule

Lab2-Singel Cycle CPU/Test_Bench.v
//Subject:     CO project 2 - Test Bench
//--------------------------------------------------------------------------------
//Version:     1
//--------------------------------------------------------------------------------
//Writer:      
//----------------------------------------------
//Date:        
//----------------------------------------------
//Description: 
//--------------------------------------------------------------------------------
`timescale 1ns/1ps

`define CYCLE_TIME 10			
`define END_COUNT 25
module TestBench;

//Internal Signals
reg         CLK;
reg         RST;
integer     count;
integer     handle;
integer     end_count;
//Greate tested modle  
Simple_Single_CPU cpu(
        .clk_i(CLK),
		.rst_i(RST)
);
 
//Main function

always #(`CYCLE_TIME/2) CLK = ~CLK;	

initial  begin
    handle = $fopen("CO_P2_Result.txt");
	CLK = 0;
    RST = 0;
	count = 0;
    end_count=25;
    #(`CYCLE_TIME)      RST = 1;
    #(`CYCLE_TIME*`END_COUNT)	$fclose(handle); $stop;
end

//Print result to "CO_P2_Result.txt"
always@(posedge CLK) begin
    count = count + 1;
	if( count == `END_COUNT ) begin 
	$display(handle, "r0=%d\nr1=%d\nr2=%d\nr3=%d\nr4=%d\nr5=%d\nr6=%d\nr7=%d\nr8=%d\nr9=%d\nr10=%d\nr11=%d\nr12=%d",
	          cpu.RF.Reg_File[0], cpu.RF.Reg_File[1], cpu.RF.Reg_File[2], cpu.RF.Reg_File[3], cpu.RF.Reg_File[4], 
			  cpu.RF.Reg_File[5], cpu.RF.Reg_File[6], cpu.RF.Reg_File[7], cpu.RF.Reg_File[8], cpu.RF.Reg_File[9], 
			  cpu.RF.Reg_File[10],cpu.RF.Reg_File[11], cpu.RF.Reg_File[12]
			  );
    $fdisplay(handle, "r0=%d\nr1=%d\nr2=%d\nr3=%d\nr4=%d\nr5=%d\nr6=%d\nr7=%d\nr8=%d\nr9=%d\nr10=%d\nr11=%d\nr12=%d",
	          cpu.RF.Reg_File[0], cpu.RF.Reg_File[1], cpu.RF.Reg_File[2], cpu.RF.Reg_File[3], cpu.RF.Reg_File[4], 
			  cpu.RF.Reg_File[5], cpu.RF.Reg_File[6], cpu.RF.Reg_File[7], cpu.RF.Reg_File[8], cpu.RF.Reg_File[9], 
			  cpu.RF.Reg_File[10],cpu.RF.Reg_File[11], cpu.RF.Reg_File[12]
			  );
	end
	else ;
end

initial begin
    $dumpfile("gtkWave.vcd");
    $dumpvars;
end

endmodule

Lab2-Singel Cycle CPU/gtkWave.vcd
$date
	Thu Apr 29 23:41:10 2021
$end
$version
	Icarus Verilog
$end
$timescale
	1ps
$end
$scope module TestBench $end
$var reg 1 ! CLK $end
$var reg 1 " RST $end
$var integer 32 # count [31:0] $end
$var integer 32 $ end_count [31:0] $end
$var integer 32 % handle [31:0] $end
$scope module cpu $end
$var wire 1 ! clk_i $end
$var wire 1 & nxt_slc $end
$var wire 1 " rst_i $end
$var wire 1 ' zeo $end
$var wire 5 ( wrt_reg [4:0] $end
$var wire 32 ) wrt_dat [31:0] $end
$var wire 32 * rd2 [31:0] $end
$var wire 32 + rd1 [31:0] $end
$var wire 32 , pc [31:0] $end
$var wire 32 - nxt_pc1 [31:0] $end
$var wire 32 . nxt_pc0 [31:0] $end
$var wire 32 / instr [31:0] $end
$var wire 32 0 fin_pc [31:0] $end
$var wire 32 1 alu_src [31:0] $end
$var wire 1 2 aluSrc $end
$var wire 3 3 aluOp [2:0] $end
$var wire 4 4 aluCTtoalu [3:0] $end
$var wire 32 5 aft_sgn [31:0] $end
$var wire 32 6 aft_sft [31:0] $end
$var wire 1 7 RegWrite $end
$var wire 1 8 RegDst $end
$var wire 1 9 Branch $end
$scope module AC $end
$var wire 6 : funct_i [5:0] $end
$var wire 1 ; op0 $end
$var wire 1 < op1 $end
$var wire 1 = op2 $end
$var wire 1 > op3 $end
$var wire 3 ? ALUOp_i [2:0] $end
$var reg 4 @ ALUCtrl_o [3:0] $end
$upscope $end
$scope module ALU $end
$var wire 4 A ctrl_i [3:0] $end
$var wire 1 ' zero_o $end
$var wire 32 B src2_i [31:0] $end
$var wire 32 C src1_i [31:0] $end
$var reg 32 D result_o [31:0] $end
$upscope $end
$scope module Adder1 $end
$var wire 32 E src1_i [31:0] $end
$var wire 32 F src2_i [31:0] $end
$var reg 32 G sum_o [31:0] $end
$upscope $end
$scope module Adder2 $end
$var wire 32 H src1_i [31:0] $end
$var wire 32 I src2_i [31:0] $end
$var reg 32 J sum_o [31:0] $end
$upscope $end
$scope module Decoder $end
$var wire 1 K addi $end
$var wire 1 L bieq $end
$var wire 6 M instr_op_i [5:0] $end
$var wire 1 N rfmt $end
$var wire 1 O slti $end
$var reg 1 2 ALUSrc_o $end
$var reg 3 P ALU_op_o [2:0] $end
$var reg 1 9 Branch_o $end
$var reg 1 8 RegDst_o $end
$var reg 1 7 RegWrite_o $end
$upscope $end
$scope module IM $end
$var wire 32 Q pc_addr_i [31:0] $end
$var reg 32 R instr_o [31:0] $end
$var integer 32 S i [31:0] $end
$upscope $end
$scope module Mux_ALUSrc $end
$var wire 1 2 select_i $end
$var wire 32 T data1_i [31:0] $end
$var wire 32 U data0_i [31:0] $end
$var reg 32 V data_o [31:0] $end
$upscope $end
$scope module Mux_PC_Source $end
$var wire 32 W data0_i [31:0] $end
$var wire 32 X data1_i [31:0] $end
$var wire 1 & select_i $end
$var reg 32 Y data_o [31:0] $end
$upscope $end
$scope module Mux_Write_Reg $end
$var wire 5 Z data0_i [4:0] $end
$var wire 5 [ data1_i [4:0] $end
$var wire 1 8 select_i $end
$var reg 5 \ data_o [4:0] $end
$upscope $end
$scope module PC $end
$var wire 1 ! clk_i $end
$var wire 32 ] pc_in_i [31:0] $end
$var wire 1 " rst_i $end
$var reg 32 ^ pc_out_o [31:0] $end
$upscope $end
$scope module RF $end
$var wire 5 _ RDaddr_i [4:0] $end
$var wire 32 ` RDdata_i [31:0] $end
$var wire 5 a RSaddr_i [4:0] $end
$var wire 32 b RSdata_o [31:0] $end
$var wire 5 c RTaddr_i [4:0] $end
$var wire 32 d RTdata_o [31:0] $end
$var wire 1 7 RegWrite_i $end
$var wire 1 ! clk_i $end
$var wire 1 " rst_i $end
$upscope $end
$scope module SE $end
$var wire 16 e data_i [15:0] $end
$var reg 32 f data_o [31:0] $end
$upscope $end
$scope module Shifter $end
$var wire 32 g data_i [31:0] $end
$var wire 32 h data_o [31:0] $end
$upscope $end
$upscope $end
$upscope $end
$enddefinitions $end
#0
$dumpvars
bx00 h
bx g
bx f
bx e
bx d
bx c
bx b
bx a
bx `
bx _
bx ^
bx ]
bx \
bx [
bx Z
bx Y
bx X
bx W
bx V
bx U
bx T
b100000 S
bx R
bx Q
bx P
xO
xN
bx M
xL
xK
bx J
bx00 I
bx H
bx G
bx F
b100 E
bx D
bx C
bx B
b0 A
b0 @
bx ?
0>
x=
x<
x;
bx :
x9
x8
x7
bx00 6
bx 5
b0 4
bx 3
x2
bx 1
bx 0
bx /
bx .
bx -
bx ,
bx +
bx *
bx )
bx (
x'
x&
b10 %
b11001 $
b0 #
0"
0!
$end
#5000
b10 4
b10 @
b10 A
1=
0&
12
17
08
09
b110 3
b110 ?
b110 P
b10 1
b10 B
b10 V
0'
b10 )
b10 D
b10 `
b110 (
b110 \
b110 _
b100 0
b100 Y
b100 ]
1K
0N
0L
b1100 -
b1100 J
b1100 X
0;
1<
0O
b1000 6
b1000 I
b1000 h
b10 5
b10 T
b10 f
b10 g
b10 e
b10 :
b1000 M
b0 *
b0 U
b0 d
b110 c
b0 +
b0 C
b0 b
b0 a
b0 [
b110 Z
b100 .
b100 G
b100 H
b100 W
b100000000001100000000000000010 /
b100000000001100000000000000010 R
b0 ,
b0 F
b0 Q
b0 ^
b1 #
1!
#10000
b10 *
b10 U
b10 d
0!
1"
#15000
b1110 )
b1110 D
b1110 `
b1110 1
b1110 B
b1110 V
b111 (
b111 \
b111 _
b1000 0
b1000 Y
b1000 ]
1;
0<
b111000 6
b111000 I
b111000 h
b1110 5
b1110 T
b1110 f
b1110 g
b1000000 -
b1000000 J
b1000000 X
b1110 e
b1110 :
b0 *
b0 U
b0 d
b111 c
b111 Z
b1000 .
b1000 G
b1000 H
b1000 W
b100000000001110000000000001110 /
b100000000001110000000000001110 R
b100 ,
b100 F
b100 Q
b100 ^
b10 #
1!
#20000
0!
#25000
b1000 (
b1000 \
b1000 _
b0 4
b0 @
b0 A
18
02
17
b1110 1
b1110 B
b1110 V
b10 3
b10 ?
b10 P
b10 )
b10 D
b10 `
b1100 0
b1100 Y
b1100 ]
1N
0K
0;
0=
b10000000010010000 6
b10000000010010000 I
b10000000010010000 h
b100000000100100 5
b100000000100100 T
b100000000100100 f
b100000000100100 g
b10000000010011100 -
b10000000010011100 J
b10000000010011100 X
b100000000100100 e
b100100 :
b0 M
b10 +
b10 C
b10 b
b110 a
b1000 [
b1100 .
b1100 G
b1100 H
b1100 W
b110001110100000000100100 /
b110001110100000000100100 R
b1000 ,
b1000 F
b1000 Q
b1000 ^
b1110 *
b1110 U
b1110 d
b11 #
1!
#30000
0!
#35000
b1110 )
b1110 D
b1110 `
b1 4
b1 @
b1 A
b1001 (
b1001 \
b1001 _
b10000 0
b10000 Y
b10000 ]
1;
b10010000010010100 6
b10010000010010100 I
b10010000010010100 h
b100100000100101 5
b100100000100101 T
b100100000100101 f
b100100000100101 g
b10010000010100100 -
b10010000010100100 J
b10010000010100100 X
b100100000100101 e
b100101 :
b1001 [
b10000 .
b10000 G
b10000 H
b10000 W
b110001110100100000100101 /
b110001110100100000100101 R
b1100 ,
b1100 F
b1100 Q
b1100 ^
b100 #
1!
#40000
0!
#45000
0'
b1 )
b1 D
b1 `
08
12
b10 4
b10 @
b10 A
b110 3
b110 ?
b110 P
b11111111111111111111111111111111 1
b11111111111111111111111111111111 B
b11111111111111111111111111111111 V
b110 (
b110 \
b110 _
b10100 0
b10100 Y
b10100 ]
0N
1K
1=
b11111111111111111111111111111100 6
b11111111111111111111111111111100 I
b11111111111111111111111111111100 h
b11111111111111111111111111111111 5
b11111111111111111111111111111111 T
b11111111111111111111111111111111 f
b11111111111111111111111111111111 g
b10000 -
b10000 J
b10000 X
b1111111111111111 e
b111111 :
b1000 M
b10 *
b10 U
b10 d
b110 c
b11111 [
b110 Z
b10100 .
b10100 G
b10100 H
b10100 W
b100000110001101111111111111111 /
b100000110001101111111111111111 R
b10000 ,
b10000 F
b10000 Q
b10000 ^
b101 #
1!
#50000
0!
#55000
b111 4
b111 @
b111 A
0;
b1 1
b1 B
b1 V
b101 3
b101 ?
b101 P
b1 (
b1 \
b1 _
b11000 0
b11000 Y
b11000 ]
1'
b0 )
b0 D
b0 `
0K
1<
1=
1O
b100 6
b100 I
b100 h
b1 5
b1 T
b1 f
b1 g
b11100 -
b11100 J
b11100 X
b1 e
b1 :
b1010 M
b1 c
b0 [
b1 Z
b11000 .
b11000 G
b11000 H
b11000 W
b101000110000010000000000000001 /
b101000110000010000000000000001 R
b10100 ,
b10100 F
b10100 Q
b10100 ^
b1 +
b1 C
b1 b
b0 *
b0 U
b0 d
b110 #
1!
#60000
0!
#65000
1&
b110 4
b110 @
b110 A
19
02
07
b0 1
b0 B
b0 V
b1 3
b1 ?
b1 P
1'
b0 )
b0 D
b0 `
b0 (
b0 \
b0 _
b1000 0
b1000 Y
b1000 ]
1L
0K
0O
b11111111111111111111111111101100 6
b11111111111111111111111111101100 I
b11111111111111111111111111101100 h
b11111111111111111111111111111011 5
b11111111111111111111111111111011 T
b11111111111111111111111111111011 f
b11111111111111111111111111111011 g
b1000 -
b1000 J
b1000 X
b1111111111111011 e
b111011 :
b100 M
b0 c
b0 +
b0 C
b0 b
b1 a
b11111 [
b0 Z
b11100 .
b11100 G
b11100 H
b11100 W
b10000001000001111111111111011 /
b10000001000001111111111111011 R
b11000 ,
b11000 F
b11000 Q
b11000 ^
b111 #
1!
#70000
0!
#75000
b0 4
b0 @
b0 A
0<
0=
0&
17
18
09
b1100 0
b1100 Y
b1100 ]
b10 3
b10 ?
b10 P
b1110 1
b1110 B
b1110 V
1'
b0 )
b0 D
b0 `
b1000 (
b1000 \
b1000 _
1N
0L
b10000000010010000 6
b10000000010010000 I
b10000000010010000 h
b100000000100100 5
b100000000100100 T
b100000000100100 f
b100000000100100 g
b10000000010011100 -
b10000000010011100 J
b10000000010011100 X
b100000000100100 e
b100100 :
b0 M
b1110 *
b1110 U
b1110 d
b111 c
b1 +
b1 C
b1 b
b110 a
b1000 [
b111 Z
b1100 .
b1100 G
b1100 H
b1100 W
b110001110100000000100100 /
b110001110100000000100100 R
b1000 ,
b1000 F
b1000 Q
b1000 ^
b1000 #
1!
#80000
0!
#85000
0'
b1111 )
b1111 D
b1111 `
b1 4
b1 @
b1 A
b1001 (
b1001 \
b1001 _
b10000 0
b10000 Y
b10000 ]
1;
b10010000010010100 6
b10010000010010100 I
b10010000010010100 h
b100100000100101 5
b100100000100101 T
b100100000100101 f
b100100000100101 g
b10010000010100100 -
b10010000010100100 J
b10010000010100100 X
b100100000100101 e
b100101 :
b1001 [
b10000 .
b10000 G
b10000 H
b10000 W
b110001110100100000100101 /
b110001110100100000100101 R
b1100 ,
b1100 F
b1100 Q
b1100 ^
b1001 #
1!
#90000
0!
#95000
1'
b0 )
b0 D
b0 `
08
12
b10 4
b10 @
b10 A
b110 3
b110 ?
b110 P
b11111111111111111111111111111111 1
b11111111111111111111111111111111 B
b11111111111111111111111111111111 V
b110 (
b110 \
b110 _
b10100 0
b10100 Y
b10100 ]
0N
1K
1=
b11111111111111111111111111111100 6
b11111111111111111111111111111100 I
b11111111111111111111111111111100 h
b11111111111111111111111111111111 5
b11111111111111111111111111111111 T
b11111111111111111111111111111111 f
b11111111111111111111111111111111 g
b10000 -
b10000 J
b10000 X
b1111111111111111 e
b111111 :
b1000 M
b1 *
b1 U
b1 d
b110 c
b11111 [
b110 Z
b10100 .
b10100 G
b10100 H
b10100 W
b100000110001101111111111111111 /
b100000110001101111111111111111 R
b10000 ,
b10000 F
b10000 Q
b10000 ^
b1010 #
1!
#100000
0!
#105000
b111 4
b111 @
b111 A
0;
b1 1
b1 B
b1 V
b101 3
b101 ?
b101 P
b1 (
b1 \
b1 _
b11000 0
b11000 Y
b11000 ]
0'
b1 )
b1 D
b1 `
0K
1<
1=
1O
b100 6
b100 I
b100 h
b1 5
b1 T
b1 f
b1 g
b11100 -
b11100 J
b11100 X
b1 e
b1 :
b1010 M
b1 c
b0 [
b1 Z
b11000 .
b11000 G
b11000 H
b11000 W
b101000110000010000000000000001 /
b101000110000010000000000000001 R
b10100 ,
b10100 F
b10100 Q
b10100 ^
b0 +
b0 C
b0 b
b0 *
b0 U
b0 d
b1011 #
1!
#110000
0!
#115000
b110 4
b110 @
b110 A
0&
19
02
07
b0 1
b0 B
b0 V
b1 3
b1 ?
b1 P
0'
b1 )
b1 D
b1 `
b0 (
b0 \
b0 _
b11100 0
b11100 Y
b11100 ]
1L
0K
0O
b11111111111111111111111111101100 6
b11111111111111111111111111101100 I
b11111111111111111111111111101100 h
b11111111111111111111111111111011 5
b11111111111111111111111111111011 T
b11111111111111111111111111111011 f
b11111111111111111111111111111011 g
b1000 -
b1000 J
b1000 X
b1111111111111011 e
b111011 :
b100 M
b0 c
b1 +
b1 C
b1 b
b1 a
b11111 [
b0 Z
b11100 .
b11100 G
b11100 H
b11100 W
b10000001000001111111111111011 /
b10000001000001111111111111011 R
b11000 ,
b11000 F
b11000 Q
b11000 ^
b0 *
b0 U
b0 d
b1100 #
1!
#120000
0!
#125000
b10 4
b10 @
b10 A
0=
17
18
09
b10 3
b10 ?
b10 P
1'
b0 )
b0 D
b0 `
b100000 0
b100000 Y
b100000 ]
1N
0L
b0 6
b0 I
b0 h
b0 5
b0 T
b0 f
b0 g
b100000 -
b100000 J
b100000 X
b0 e
b0 :
b0 M
b0 +
b0 C
b0 b
b0 a
b0 [
b100000 .
b100000 G
b100000 H
b100000 W
b0 /
b0 R
b11100 ,
b11100 F
b11100 Q
b11100 ^
b1101 #
1!
#130000
0!
#135000
b100100 0
b100100 Y
b100100 ]
b100100 -
b100100 J
b100100 X
b100100 .
b100100 G
b100100 H
b100100 W
b100000 ,
b100000 F
b100000 Q
b100000 ^
b1110 #
1!
#140000
0!
#145000
b101000 0
b101000 Y
b101000 ]
b101000 -
b101000 J
b101000 X
b101000 .
b101000 G
b101000 H
b101000 W
b100100 ,
b100100 F
b100100 Q
b100100 ^
b1111 #
1!
#150000
0!
#155000
b101100 0
b101100 Y
b101100 ]
b101100 -
b101100 J
b101100 X
b101100 .
b101100 G
b101100 H
b101100 W
b101000 ,
b101000 F
b101000 Q
b101000 ^
b10000 #
1!
#160000
0!
#165000
b110000 0
b110000 Y
b110000 ]
b110000 -
b110000 J
b110000 X
b110000 .
b110000 G
b110000 H
b110000 W
b101100 ,
b101100 F
b101100 Q
b101100 ^
b10001 #
1!
#170000
0!
#175000
b110100 0
b110100 Y
b110100 ]
b110100 -
b110100 J
b110100 X
b110100 .
b110100 G
b110100 H
b110100 W
b110000 ,
b110000 F
b110000 Q
b110000 ^
b10010 #
1!
#180000
0!
#185000
b111000 0
b111000 Y
b111000 ]
b111000 -
b111000 J
b111000 X
b111000 .
b111000 G
b111000 H
b111000 W
b110100 ,
b110100 F
b110100 Q
b110100 ^
b10011 #
1!
#190000
0!
#195000
b111100 0
b111100 Y
b111100 ]
b111100 -
b111100 J
b111100 X
b111100 .
b111100 G
b111100 H
b111100 W
b111000 ,
b111000 F
b111000 Q
b111000 ^
b10100 #
1!
#200000
0!
#205000
b1000000 0
b1000000 Y
b1000000 ]
b1000000 -
b1000000 J
b1000000 X
b1000000 .
b1000000 G
b1000000 H
b1000000 W
b111100 ,
b111100 F
b111100 Q
b111100 ^
b10101 #
1!
#210000
0!
#215000
b1000100 0
b1000100 Y
b1000100 ]
b1000100 -
b1000100 J
b1000100 X
b1000100 .
b1000100 G
b1000100 H
b1000100 W
b1000000 ,
b1000000 F
b1000000 Q
b1000000 ^
b10110 #
1!
#220000
0!
